setup.py
IES.egg-info/PKG-INFO
IES.egg-info/SOURCES.txt
IES.egg-info/dependency_links.txt
IES.egg-info/requires.txt
IES.egg-info/top_level.txt
ies/__init__.py
ies/_version.py
ies/local_runner.py
strategycontainer/__init__.py
strategycontainer/api.py
strategycontainer/commission.py
strategycontainer/data.py
strategycontainer/exception.py
strategycontainer/ips_api.py
strategycontainer/jsonencoder.py
strategycontainer/model.py
strategycontainer/server.py
strategycontainer/slippage.py
strategycontainer/var.py
strategycontainer/lib/_factorize.pyx
strategycontainer/lib/_float64window.pyx
strategycontainer/lib/_int64window.pyx
strategycontainer/lib/_labelwindow.pyx
strategycontainer/lib/_uint8window.pyx
strategycontainer/lib/adjustment.pyx
strategycontainer/lib/rank.pyx
strategycontainer/lib/__init__.py
strategycontainer/lib/_factorize.pyx
strategycontainer/lib/_float64window.pyx
strategycontainer/lib/_int64window.pyx
strategycontainer/lib/_labelwindow.pyx
strategycontainer/lib/_uint8window.pyx
strategycontainer/lib/adjusted_array.py
strategycontainer/lib/adjustment.pyx
strategycontainer/lib/labelarray.py
strategycontainer/lib/normalize.py
strategycontainer/lib/quantiles.py
strategycontainer/lib/rank.pyx
strategycontainer/tsp/__init__.py
strategycontainer/tsp/api_utils.py
strategycontainer/tsp/common.py
strategycontainer/tsp/downsample_helpers.py
strategycontainer/tsp/dtypes.py
strategycontainer/tsp/engine.py
strategycontainer/tsp/expression.py
strategycontainer/tsp/factor_out_cache.py
strategycontainer/tsp/graph.py
strategycontainer/tsp/mixins.py
strategycontainer/tsp/sentinels.py
strategycontainer/tsp/term.py
strategycontainer/tsp/tsp.py
strategycontainer/tsp/visualize.py
strategycontainer/tsp/classifiers/__init__.py
strategycontainer/tsp/classifiers/classifier.py
strategycontainer/tsp/data/__init__.py
strategycontainer/tsp/data/dataset.py
strategycontainer/tsp/data/equity_fundamental.py
strategycontainer/tsp/data/equity_indicator.py
strategycontainer/tsp/data/equity_market1indicator.py
strategycontainer/tsp/data/equity_pricing.py
strategycontainer/tsp/factors/__init__.py
